baricadr/__init__.py
baricadr/client.py
baricadr/exceptions.py
baricadr/file/__init__.py
baricadr/task/__init__.py
barique/__init__.py
barique/cli.py
barique/config.py
barique/decorators.py
barique/io.py
barique/commands/__init__.py
barique/commands/cmd_file.py
barique/commands/cmd_init.py
barique/commands/cmd_task.py
barique/commands/file/__init__.py
barique/commands/file/freeze.py
barique/commands/file/list.py
barique/commands/file/pull.py
barique/commands/file/tree.py
barique/commands/task/__init__.py
barique/commands/task/list.py
barique/commands/task/log.py
barique/commands/task/remove.py
barique/commands/task/show.py
barique/commands/task/zombies.py
barique-0.1.4.dist-info/LICENSE
barique-0.1.4.dist-info/METADATA
barique-0.1.4.dist-info/WHEEL
barique-0.1.4.dist-info/entry_points.txt
barique-0.1.4.dist-info/top_level.txt
barique-0.1.4.dist-info/RECORD
