Metadata-Version: 2.1
Name: barique
Version: 0.1.4
Summary: Baricadr CLI
Home-page: https://github.com/baricadr/barique
Author: Mateo Boudet
Author-email: mateo.boudet@inrae.fr
License: MIT
Platform: Posix; MacOS X; Windows
Classifier: Development Status :: 4 - Beta
Classifier: Intended Audience :: Developers
Classifier: License :: OSI Approved :: MIT License
Classifier: Operating System :: OS Independent
Classifier: Topic :: Scientific/Engineering
Classifier: Programming Language :: Python :: 3.7
License-File: LICENSE
Requires-Dist: wrapt
Requires-Dist: click
Requires-Dist: future
Requires-Dist: requests
Requires-Dist: pyyaml
Requires-Dist: treelib
